{
  "$schema": "https://schema.management.azure.com/schemas/2019-08-01/managementGroupDeploymentTemplate.json#",
  "contentVersion": "1.0.0.0",
  "resources": [
    {
      "type": "Microsoft.Authorization/policyDefinitions",
      "name": "diagnostics-sub-deploy-policy",
      "apiVersion": "2019-09-01",
      "properties": {
        "displayName": "Deploy Diagnostics & Metrics for Subscription to a Log Analytics workspace",
        "description": "Apply diagnostic & metric settings for Subscription to stream data to a Log Analytics workspace when any Subscription which is missing this diagnostic settings is created or updated.",
        "metadata": {
          "category": "Monitoring",
          "version": "1.0.0.0"
        },
        "mode": "All",
        "parameters": {
          "profileName": {
            "type": "string",
            "metadata": {
              "displayName": "Profile name",
              "description": "The diagnostic settings profile name"
            },
            "defaultValue": "setbypolicy_logAnalytics"
          },
          "logAnalytics": {
            "type": "string",
            "metadata": {
              "displayName": "Log Analytics workspace",
              "description": "Select Log Analytics workspace from dropdown list. If this workspace is outside of the scope of the assignment you must manually grant 'Log Analytics Contributor' permissions (or similar) to the policy assignment's principal ID.",
              "strongType": "omsWorkspace",
              "assignPermissions": true
            }
          }
        },
        "policyType": "Custom",
        "policyRule": {
          "if": {
            "field": "type",
            "equals": "Microsoft.Resources/subscriptions"
          },
          "then": {
            "effect": "deployIfNotExists",
            "details": {
              "type": "microsoft.insights/diagnosticSettings",
              "existenceCondition": {
                "allOf": [
                  {
                    "field": "Microsoft.Insights/diagnosticSettings/workspaceId",
                    "equals": "[[parameters('logAnalytics')]"
                  }
                ]
              },
              "roleDefinitionIds": [
                "/providers/microsoft.authorization/roleDefinitions/749f88d5-cbae-40b8-bcfc-e573ddc772fa",
                "/providers/microsoft.authorization/roleDefinitions/92aaf0da-9dab-42b6-94a3-d43ce8d16293"
              ],
              "deployment": {
                "properties": {
                  "mode": "incremental",
                  "template": {
                    "$schema": "https://schema.management.azure.com/schemas/2018-05-01/subscriptionDeploymentTemplate.json#",
                    "contentVersion": "1.0.0.0",
                    "parameters": {
                      "profileName": {
                        "type": "string"
                      },
                      "logAnalytics": {
                        "type": "string"
                      }
                    },
                    "variables": {},
                    "resources": [
                      {
                        "type": "microsoft.insights/diagnosticSettings",
                        "apiVersion": "2017-05-01-preview",
                        "name": "[[parameters('profileName')]",
                        "properties": {
                          "workspaceId": "[[parameters('logAnalytics')]",
                          "logs": [
                            {
                              "category": "Administrative",
                              "enabled": true
                            },
                            {
                              "category": "Security",
                              "enabled": true
                            },
                            {
                              "category": "ServiceHealth",
                              "enabled": true
                            },
                            {
                              "category": "Alert",
                              "enabled": true
                            },
                            {
                              "category": "Recommendation",
                              "enabled": true
                            },
                            {
                              "category": "Policy",
                              "enabled": true
                            },
                            {
                              "category": "Autoscale",
                              "enabled": true
                            },
                            {
                              "category": "ResourceHealth",
                              "enabled": true
                            }
                          ]
                        }
                      }
                    ],
                    "outputs": {}
                  },
                  "parameters": {
                    "logAnalytics": {
                      "value": "[[parameters('logAnalytics')]"
                    },
                    "profileName": {
                      "value": "[[parameters('profileName')]"
                    }
                  }
                },
                "location": "eastus"
              },
              "deploymentScope": "subscription"
            }
          }
        }
      }
    }
  ]
}